[
    {
        "Id" : "C36",
        "TagId" : "04A097D2826C80"
    },
    {
        "Id" : "C45",
        "TagId" : "04D8252A655580"
    },
    {
        "Id" : "D8011",
        "TagId" : "044D312A655580"
    },
    {
        "Id" : "N66",
        "TagId" : "048197D2826C80"
    },
    {
        "Id" : "O11",
        "TagId" : "048097D2826C80"
    },
    {
        "Id" : "O12",
        "TagId" : "046197D2826C80"
    },
    {
        "Id" : "O45",
        "TagId" : "04C097D2826C80"
    },
    {
        "Id" : "04F6",
        "TagId" : "04F6242A655580"
    },
    {
        "Id" : "V65",
        "TagId" : "04BC2A2A655580"
    }
]